MicroTokenizer/__init__.py
MicroTokenizer/pipeline.py
MicroTokenizer/cli/__init__.py
MicroTokenizer/cli/main.py
MicroTokenizer/cli/commands/__init__.py
MicroTokenizer/cli/commands/train.py
MicroTokenizer/data_structures/__init__.py
MicroTokenizer/data_structures/dictionary.py
MicroTokenizer/data_structures/graph_builder.py
MicroTokenizer/data_structures/non_recursive_algorithm.py
MicroTokenizer/data_structures/train_dictionary.py
MicroTokenizer/data_structures/trie_algorithm.py
MicroTokenizer/encoding/BMES.py
MicroTokenizer/encoding/__init__.py
MicroTokenizer/ensemble/__init__.py
MicroTokenizer/ensemble/merge_solutions.py
MicroTokenizer/experimental/__init__.py
MicroTokenizer/model_data/A.pickle
MicroTokenizer/model_data/B.pickle
MicroTokenizer/model_data/dict.txt
MicroTokenizer/model_data/feature_func_list.pickle
MicroTokenizer/model_data/model.crfsuite
MicroTokenizer/model_data/vocabulary.pickle
MicroTokenizer/tokenizers/BMES.py
MicroTokenizer/tokenizers/__init__.py
MicroTokenizer/tokenizers/base_tokenizer.py
MicroTokenizer/tokenizers/dag_tokenizer.py
MicroTokenizer/tokenizers/hmm_tokenizer.py
MicroTokenizer/tokenizers/whitespace_split_tokenizer.py
MicroTokenizer/tokenizers/crf/__init__.py
MicroTokenizer/tokenizers/crf/tokenizer.py
MicroTokenizer/tokenizers/crf/trainer.py
MicroTokenizer/tokenizers/ensemble/__init__.py
MicroTokenizer/tokenizers/ensemble/tokenizer.py
MicroTokenizer/tokenizers/max_match/__init__.py
MicroTokenizer/tokenizers/max_match/backward.py
MicroTokenizer/tokenizers/max_match/bidirectional.py
MicroTokenizer/tokenizers/max_match/forward.py
MicroTokenizer/tokenizers/unicode_script/__init__.py
MicroTokenizer/tokenizers/unicode_script/generate_script_data.py
MicroTokenizer/tokenizers/unicode_script/script_data.py
MicroTokenizer/tokenizers/unicode_script/token.py
MicroTokenizer/tokenizers/unicode_script/tokenizer.py
MicroTokenizer-0.21.3.data/data/A.pickle
MicroTokenizer-0.21.3.data/data/B.pickle
MicroTokenizer-0.21.3.data/data/dict.txt
MicroTokenizer-0.21.3.dist-info/AUTHORS.rst
MicroTokenizer-0.21.3.dist-info/LICENSE
MicroTokenizer-0.21.3.dist-info/METADATA
MicroTokenizer-0.21.3.dist-info/WHEEL
MicroTokenizer-0.21.3.dist-info/entry_points.txt
MicroTokenizer-0.21.3.dist-info/top_level.txt
MicroTokenizer-0.21.3.dist-info/RECORD
