Metadata-Version: 2.1
Name: MicroTokenizer
Version: 0.21.3
Summary: A micro tokenizer for Chinese
Home-page: https://github.com/howl-anderson/MicroTokenizer
Author: Xiaoquan Kong
Author-email: u1mail2me@gmail.com
License: MIT license
Keywords: MicroTokenizer
Classifier: Development Status :: 2 - Pre-Alpha
Classifier: Intended Audience :: Developers
Classifier: License :: OSI Approved :: MIT License
Classifier: Natural Language :: English
Classifier: Programming Language :: Python :: 3
Classifier: Programming Language :: Python :: 3.5
Classifier: Programming Language :: Python :: 3.6
License-File: LICENSE
License-File: AUTHORS.rst
Requires-Dist: networkx
Requires-Dist: MicroHMM
Requires-Dist: python-crfsuite
Requires-Dist: pyyaml
